httpx_auth_awssigv4/__init__.py
httpx_auth_awssigv4/auth.py
httpx_auth_awssigv4-0.1.4.dist-info/LICENSE
httpx_auth_awssigv4-0.1.4.dist-info/WHEEL
httpx_auth_awssigv4-0.1.4.dist-info/METADATA
httpx_auth_awssigv4-0.1.4.dist-info/RECORD
